[
  {
    "__docId__": 0,
    "kind": "file",
    "static": true,
    "variation": null,
    "name": "components/Comment.js",
    "memberof": null,
    "longname": "components/Comment.js",
    "access": null,
    "description": null,
    "lineNumber": 1,
    "content": "import React from 'react';\r\n\r\n/**\r\n * コメントアイテムクラス\r\n */\r\nexport default class Comment extends React.Component {\r\n    /**\r\n     * コンストラクタ\r\n     * @override\r\n     */\r\n    render() {\r\n        return (\r\n            <li className='md-comment'>\r\n                <span className='md-comment-title l-block'>{this.props.commentTitle}</span>\r\n                <span className='md-comment-dateTime l-block'>2015/11/06 9:12</span>\r\n                <span className='md-comment-text l-block'>Comment text</span>\r\n            </li>\r\n        );\r\n    }\r\n}\r\n"
  },
  {
    "__docId__": 1,
    "kind": "class",
    "static": true,
    "variation": null,
    "name": "Comment",
    "memberof": "components/Comment.js",
    "longname": "components/Comment.js~Comment",
    "access": null,
    "export": true,
    "importPath": "react_es6/components/Comment.js",
    "importStyle": "Comment",
    "description": "コメントアイテムクラス",
    "lineNumber": 6,
    "interface": false,
    "extends": [
      "react~React.Component"
    ]
  },
  {
    "__docId__": 2,
    "kind": "method",
    "static": false,
    "variation": null,
    "name": "render",
    "memberof": "components/Comment.js~Comment",
    "longname": "components/Comment.js~Comment#render",
    "access": null,
    "description": "コンストラクタ",
    "lineNumber": 11,
    "params": [],
    "return": {
      "types": [
        "*"
      ]
    },
    "override": true,
    "generator": false
  },
  {
    "__docId__": 3,
    "kind": "file",
    "static": true,
    "variation": null,
    "name": "components/CommentBox.js",
    "memberof": null,
    "longname": "components/CommentBox.js",
    "access": null,
    "description": null,
    "lineNumber": 1,
    "content": "import React       from 'react';\r\nimport CommentList from './CommentList';\r\nimport CommentForm from './Commentform';\r\n\r\n/**\r\n * コメントボックスクラス\r\n */\r\nexport default class CommentBox extends React.Component {\r\n    /**\r\n     * コンストラクタ\r\n     * @override\r\n     */\r\n    constructor(props) {\r\n        super(props);\r\n    }\r\n\r\n    /**\r\n     * @override\r\n     */\r\n    render() {\r\n        return (\r\n            <div className='commentBox'>\r\n                <CommentList />\r\n                <CommentForm />\r\n            </div>\r\n        );\r\n    }\r\n}"
  },
  {
    "__docId__": 4,
    "kind": "class",
    "static": true,
    "variation": null,
    "name": "CommentBox",
    "memberof": "components/CommentBox.js",
    "longname": "components/CommentBox.js~CommentBox",
    "access": null,
    "export": true,
    "importPath": "react_es6/components/CommentBox.js",
    "importStyle": "CommentBox",
    "description": "コメントボックスクラス",
    "lineNumber": 8,
    "interface": false,
    "extends": [
      "react~React.Component"
    ]
  },
  {
    "__docId__": 5,
    "kind": "constructor",
    "static": false,
    "variation": null,
    "name": "constructor",
    "memberof": "components/CommentBox.js~CommentBox",
    "longname": "components/CommentBox.js~CommentBox#constructor",
    "access": null,
    "description": "コンストラクタ",
    "lineNumber": 13,
    "params": [
      {
        "name": "props",
        "types": [
          "*"
        ]
      }
    ],
    "override": true,
    "generator": false
  },
  {
    "__docId__": 6,
    "kind": "method",
    "static": false,
    "variation": null,
    "name": "render",
    "memberof": "components/CommentBox.js~CommentBox",
    "longname": "components/CommentBox.js~CommentBox#render",
    "access": null,
    "description": null,
    "lineNumber": 20,
    "params": [],
    "return": {
      "types": [
        "*"
      ]
    },
    "override": true,
    "generator": false
  },
  {
    "__docId__": 7,
    "kind": "file",
    "static": true,
    "variation": null,
    "name": "components/CommentForm.js",
    "memberof": null,
    "longname": "components/CommentForm.js",
    "access": null,
    "description": null,
    "lineNumber": 1,
    "content": "import React  from 'react';\r\nimport Marked from 'marked';\r\nimport _      from 'lodash';\r\n\r\n/**\r\n * 新規コメント作成フォームクラス\r\n */\r\nexport default class CommentForm extends React.Component {\r\n    /**\r\n     * コンストラクタ\r\n     * @override\r\n     */\r\n    constructor(props) {\r\n        super(props);\r\n\r\n        /**\r\n         * @type {Object}\r\n         */\r\n        this.state = {\r\n            newCommentText: ''\r\n        };\r\n    }\r\n\r\n    /**\r\n     * @override\r\n     */\r\n    componentDidMount() {\r\n        this.setState({\r\n            newCommentTextLength: this.state.newCommentText.length,\r\n            newCommentTextLines : this._getTextLines(this.state.newCommentText)\r\n        });\r\n    }\r\n\r\n    /**\r\n     * 入力されたコメントを state に反映する\r\n     * @param  {Object} e イベントオブジェクト\r\n     */\r\n    _changeNewCommentText(e) {\r\n        const commentText = e.target.value;\r\n\r\n        this.setState({\r\n            newCommentText      : commentText,\r\n            newCommentTextLength: commentText.length,\r\n            newCommentTextLines : this._getTextLines(commentText)\r\n        });\r\n    }\r\n\r\n    /**\r\n     * 入力されたコメントの行数を返却する\r\n     * @param  {String} s コメント\r\n     * @return {Number}   コメントの行数\r\n     */\r\n    _getTextLines(s) {\r\n        return s.split('\\n').length;\r\n    }\r\n\r\n    /**\r\n     * コメントを localStorage に保存する\r\n     */\r\n    _saveNewComment() {\r\n        /**\r\n         * @todo ハードコーディングを撤廃しちゃんと一意なキーで保存できるようにする\r\n         */\r\n        localStorage.setItem('newComment', this.state.newCommentText);\r\n    }\r\n\r\n    /**\r\n     * @override\r\n     */\r\n    render() {\r\n        const markedCommentText = Marked(this.state.newCommentText, { sanitize: true });\r\n        const lineNumbers       = this.state.newCommentTextLines;\r\n\r\n        return (\r\n            <div id=\"commentForm\" className=\"l-inline-block\">\r\n                <div id=\"commentForm__box-edit-tag\">\r\n                    <input type=\"text\" />\r\n                </div>\r\n                <div id=\"commentForm__wrapper-edit\" className=\"l-horizontal\">\r\n                    <h2>New comment</h2>\r\n                    <div id=\"commentForm__wrapper-edit__box-edit\">\r\n                        <div id=\"commentForm__wrapper-edit__box-edit__box-line-numbers\" className=\"l-horizontal\">\r\n                            {_.range(0, this.state.newCommentTextLines).map(l => <span className=\"l-line-number\">{l + 1}</span>)}\r\n                        </div>\r\n                        <textarea id=\"commentForm__wrapper-edit__box-edit__textarea\" onChange={this._changeNewCommentText.bind(this)} />\r\n                    </div>\r\n                </div>\r\n                <div id=\"commentForm__box-preview\" className=\"l-horizontal\">\r\n                    <h2>Realtime preview</h2>\r\n                    <span dangerouslySetInnerHTML={{__html: markedCommentText}} />\r\n                </div>\r\n                <button type=\"button\" onClick={this._saveNewComment.bind(this)}>Save</button>\r\n            </div>\r\n        );\r\n    }\r\n}\r\n"
  },
  {
    "__docId__": 8,
    "kind": "class",
    "static": true,
    "variation": null,
    "name": "CommentForm",
    "memberof": "components/CommentForm.js",
    "longname": "components/CommentForm.js~CommentForm",
    "access": null,
    "export": true,
    "importPath": "react_es6/components/CommentForm.js",
    "importStyle": "CommentForm",
    "description": "新規コメント作成フォームクラス",
    "lineNumber": 8,
    "interface": false,
    "extends": [
      "react~React.Component"
    ]
  },
  {
    "__docId__": 9,
    "kind": "constructor",
    "static": false,
    "variation": null,
    "name": "constructor",
    "memberof": "components/CommentForm.js~CommentForm",
    "longname": "components/CommentForm.js~CommentForm#constructor",
    "access": null,
    "description": "コンストラクタ",
    "lineNumber": 13,
    "params": [
      {
        "name": "props",
        "types": [
          "*"
        ]
      }
    ],
    "override": true,
    "generator": false
  },
  {
    "__docId__": 10,
    "kind": "member",
    "static": false,
    "variation": null,
    "name": "state",
    "memberof": "components/CommentForm.js~CommentForm",
    "longname": "components/CommentForm.js~CommentForm#state",
    "access": null,
    "description": null,
    "lineNumber": 19,
    "type": {
      "nullable": null,
      "types": [
        "Object"
      ],
      "spread": false,
      "description": null
    }
  },
  {
    "__docId__": 11,
    "kind": "method",
    "static": false,
    "variation": null,
    "name": "componentDidMount",
    "memberof": "components/CommentForm.js~CommentForm",
    "longname": "components/CommentForm.js~CommentForm#componentDidMount",
    "access": null,
    "description": null,
    "lineNumber": 27,
    "params": [],
    "override": true,
    "generator": false
  },
  {
    "__docId__": 12,
    "kind": "method",
    "static": false,
    "variation": null,
    "name": "_changeNewCommentText",
    "memberof": "components/CommentForm.js~CommentForm",
    "longname": "components/CommentForm.js~CommentForm#_changeNewCommentText",
    "access": null,
    "description": "入力されたコメントを state に反映する",
    "lineNumber": 38,
    "params": [
      {
        "nullable": null,
        "types": [
          "Object"
        ],
        "spread": false,
        "optional": false,
        "name": "e",
        "description": "イベントオブジェクト"
      }
    ],
    "generator": false
  },
  {
    "__docId__": 13,
    "kind": "method",
    "static": false,
    "variation": null,
    "name": "_getTextLines",
    "memberof": "components/CommentForm.js~CommentForm",
    "longname": "components/CommentForm.js~CommentForm#_getTextLines",
    "access": null,
    "description": "入力されたコメントの行数を返却する",
    "lineNumber": 53,
    "params": [
      {
        "nullable": null,
        "types": [
          "String"
        ],
        "spread": false,
        "optional": false,
        "name": "s",
        "description": "コメント"
      }
    ],
    "return": {
      "nullable": null,
      "types": [
        "Number"
      ],
      "spread": false,
      "description": "コメントの行数"
    },
    "generator": false
  },
  {
    "__docId__": 14,
    "kind": "method",
    "static": false,
    "variation": null,
    "name": "_saveNewComment",
    "memberof": "components/CommentForm.js~CommentForm",
    "longname": "components/CommentForm.js~CommentForm#_saveNewComment",
    "access": null,
    "description": "コメントを localStorage に保存する",
    "lineNumber": 60,
    "params": [],
    "generator": false
  },
  {
    "__docId__": 15,
    "kind": "method",
    "static": false,
    "variation": null,
    "name": "render",
    "memberof": "components/CommentForm.js~CommentForm",
    "longname": "components/CommentForm.js~CommentForm#render",
    "access": null,
    "description": null,
    "lineNumber": 70,
    "params": [],
    "return": {
      "types": [
        "*"
      ]
    },
    "override": true,
    "generator": false
  },
  {
    "__docId__": 16,
    "kind": "file",
    "static": true,
    "variation": null,
    "name": "components/CommentList.js",
    "memberof": null,
    "longname": "components/CommentList.js",
    "access": null,
    "description": null,
    "lineNumber": 1,
    "content": "import React              from 'react';\r\nimport Comment            from './Comment';\r\nimport _                  from 'lodash';\r\nimport CSSTransitionGroup from 'react-addons-css-transition-group';\r\n\r\n/**\r\n * コメントアイテム一覧クラス\r\n */\r\nexport default class CommentList extends React.Component {\r\n    /**\r\n     * コンストラクタ\r\n     * @override\r\n     */\r\n    constructor(props) {\r\n        super(props);\r\n        /**\r\n         * @type {String}\r\n         */\r\n        this.displayName = 'CommentList';\r\n\r\n        /**\r\n         * @type {Object}\r\n         */\r\n        this.state = {\r\n            comments: [\r\n                { commentTitle: 'Comm1' },\r\n                { commentTitle: 'Comm1-1' },\r\n                { commentTitle: 'Comm1-2' },\r\n                { commentTitle: 'Comm1-3' },\r\n                { commentTitle: 'Comm1-4' },\r\n                { commentTitle: 'Comm1-5' },\r\n                { commentTitle: 'Comm1-6' },\r\n                { commentTitle: 'Comm1-7' },\r\n                { commentTitle: 'Comm1-8' },\r\n                { commentTitle: 'Comm1-9' },\r\n                { commentTitle: 'Comm2-1' },\r\n                { commentTitle: 'Comm2-2' },\r\n                { commentTitle: 'Comm2-3' },\r\n                { commentTitle: 'Comm2-4' }\r\n            ],\r\n            searchedComments: [\r\n                { commentTitle: 'Comm1' },\r\n                { commentTitle: 'Comm1-1' },\r\n                { commentTitle: 'Comm1-2' },\r\n                { commentTitle: 'Comm1-3' },\r\n                { commentTitle: 'Comm1-4' },\r\n                { commentTitle: 'Comm1-5' },\r\n                { commentTitle: 'Comm1-6' },\r\n                { commentTitle: 'Comm1-7' },\r\n                { commentTitle: 'Comm1-8' },\r\n                { commentTitle: 'Comm1-9' },\r\n                { commentTitle: 'Comm2-1' },\r\n                { commentTitle: 'Comm2-2' },\r\n                { commentTitle: 'Comm2-3' },\r\n                { commentTitle: 'Comm2-4' }\r\n            ]\r\n        };\r\n    }\r\n\r\n    /**\r\n     * コメントアイテムをインクリメンタルサーチする\r\n     * @param  {Object} e イベントオブジェクト\r\n     */\r\n    _searchIncremental(e) {\r\n        const searchWord = e.target.value;\r\n\r\n        this.setState({\r\n            searchedComments: _.filter(this.state.comments, c => {\r\n                return c.commentTitle.includes(searchWord);\r\n            })\r\n        });\r\n    }\r\n\r\n    /**\r\n     * @override\r\n     */\r\n    render() {\r\n        return (\r\n            <nav id='nav' className='l-inline-block'>\r\n                <ul id='nav__comment-list'>\r\n                    <li className='md-comment'>\r\n                        <input type='text' className='md-keyword-search-comment' onChange={this._searchIncremental.bind(this)} />\r\n                        <span className=\"fa fa-search\"></span>\r\n                    </li>\r\n                    <CSSTransitionGroup transitionName='am-fade-opacity'>\r\n                        {this.state.searchedComments.map(s => <Comment key={s.commentTitle} commentTitle={s.commentTitle} />)}\r\n                    </CSSTransitionGroup>\r\n                </ul>\r\n            </nav>\r\n        );\r\n    }\r\n}"
  },
  {
    "__docId__": 17,
    "kind": "class",
    "static": true,
    "variation": null,
    "name": "CommentList",
    "memberof": "components/CommentList.js",
    "longname": "components/CommentList.js~CommentList",
    "access": null,
    "export": true,
    "importPath": "react_es6/components/CommentList.js",
    "importStyle": "CommentList",
    "description": "コメントアイテム一覧クラス",
    "lineNumber": 9,
    "interface": false,
    "extends": [
      "react~React.Component"
    ]
  },
  {
    "__docId__": 18,
    "kind": "constructor",
    "static": false,
    "variation": null,
    "name": "constructor",
    "memberof": "components/CommentList.js~CommentList",
    "longname": "components/CommentList.js~CommentList#constructor",
    "access": null,
    "description": "コンストラクタ",
    "lineNumber": 14,
    "params": [
      {
        "name": "props",
        "types": [
          "*"
        ]
      }
    ],
    "override": true,
    "generator": false
  },
  {
    "__docId__": 19,
    "kind": "member",
    "static": false,
    "variation": null,
    "name": "displayName",
    "memberof": "components/CommentList.js~CommentList",
    "longname": "components/CommentList.js~CommentList#displayName",
    "access": null,
    "description": null,
    "lineNumber": 19,
    "type": {
      "nullable": null,
      "types": [
        "String"
      ],
      "spread": false,
      "description": null
    }
  },
  {
    "__docId__": 20,
    "kind": "member",
    "static": false,
    "variation": null,
    "name": "state",
    "memberof": "components/CommentList.js~CommentList",
    "longname": "components/CommentList.js~CommentList#state",
    "access": null,
    "description": null,
    "lineNumber": 24,
    "type": {
      "nullable": null,
      "types": [
        "Object"
      ],
      "spread": false,
      "description": null
    }
  },
  {
    "__docId__": 21,
    "kind": "method",
    "static": false,
    "variation": null,
    "name": "_searchIncremental",
    "memberof": "components/CommentList.js~CommentList",
    "longname": "components/CommentList.js~CommentList#_searchIncremental",
    "access": null,
    "description": "コメントアイテムをインクリメンタルサーチする",
    "lineNumber": 64,
    "params": [
      {
        "nullable": null,
        "types": [
          "Object"
        ],
        "spread": false,
        "optional": false,
        "name": "e",
        "description": "イベントオブジェクト"
      }
    ],
    "generator": false
  },
  {
    "__docId__": 22,
    "kind": "method",
    "static": false,
    "variation": null,
    "name": "render",
    "memberof": "components/CommentList.js~CommentList",
    "longname": "components/CommentList.js~CommentList#render",
    "access": null,
    "description": null,
    "lineNumber": 77,
    "params": [],
    "return": {
      "types": [
        "*"
      ]
    },
    "override": true,
    "generator": false
  },
  {
    "__docId__": 24,
    "kind": "external",
    "static": true,
    "variation": null,
    "name": "Infinity",
    "externalLink": "https://developer.mozilla.org/en-US/docs/Web/JavaScript/Reference/Global_Objects/Infinity",
    "memberof": "BuiltinExternal/ECMAScriptExternal.js",
    "longname": "BuiltinExternal/ECMAScriptExternal.js~Infinity",
    "access": null,
    "description": null,
    "builtinExternal": true
  },
  {
    "__docId__": 25,
    "kind": "external",
    "static": true,
    "variation": null,
    "name": "NaN",
    "externalLink": "https://developer.mozilla.org/en-US/docs/Web/JavaScript/Reference/Global_Objects/NaN",
    "memberof": "BuiltinExternal/ECMAScriptExternal.js",
    "longname": "BuiltinExternal/ECMAScriptExternal.js~NaN",
    "access": null,
    "description": null,
    "builtinExternal": true
  },
  {
    "__docId__": 26,
    "kind": "external",
    "static": true,
    "variation": null,
    "name": "undefined",
    "externalLink": "https://developer.mozilla.org/en-US/docs/Web/JavaScript/Reference/Global_Objects/undefined",
    "memberof": "BuiltinExternal/ECMAScriptExternal.js",
    "longname": "BuiltinExternal/ECMAScriptExternal.js~undefined",
    "access": null,
    "description": null,
    "builtinExternal": true
  },
  {
    "__docId__": 27,
    "kind": "external",
    "static": true,
    "variation": null,
    "name": "null",
    "externalLink": "https://developer.mozilla.org/en-US/docs/Web/JavaScript/Reference/Global_Objects/null",
    "memberof": "BuiltinExternal/ECMAScriptExternal.js",
    "longname": "BuiltinExternal/ECMAScriptExternal.js~null",
    "access": null,
    "description": null,
    "builtinExternal": true
  },
  {
    "__docId__": 28,
    "kind": "external",
    "static": true,
    "variation": null,
    "name": "Object",
    "externalLink": "https://developer.mozilla.org/en-US/docs/Web/JavaScript/Reference/Global_Objects/Object",
    "memberof": "BuiltinExternal/ECMAScriptExternal.js",
    "longname": "BuiltinExternal/ECMAScriptExternal.js~Object",
    "access": null,
    "description": null,
    "builtinExternal": true
  },
  {
    "__docId__": 29,
    "kind": "external",
    "static": true,
    "variation": null,
    "name": "object",
    "externalLink": "https://developer.mozilla.org/en-US/docs/Web/JavaScript/Reference/Global_Objects/Object",
    "memberof": "BuiltinExternal/ECMAScriptExternal.js",
    "longname": "BuiltinExternal/ECMAScriptExternal.js~object",
    "access": null,
    "description": null,
    "builtinExternal": true
  },
  {
    "__docId__": 30,
    "kind": "external",
    "static": true,
    "variation": null,
    "name": "Function",
    "externalLink": "https://developer.mozilla.org/en-US/docs/Web/JavaScript/Reference/Global_Objects/Function",
    "memberof": "BuiltinExternal/ECMAScriptExternal.js",
    "longname": "BuiltinExternal/ECMAScriptExternal.js~Function",
    "access": null,
    "description": null,
    "builtinExternal": true
  },
  {
    "__docId__": 31,
    "kind": "external",
    "static": true,
    "variation": null,
    "name": "function",
    "externalLink": "https://developer.mozilla.org/en-US/docs/Web/JavaScript/Reference/Global_Objects/Function",
    "memberof": "BuiltinExternal/ECMAScriptExternal.js",
    "longname": "BuiltinExternal/ECMAScriptExternal.js~function",
    "access": null,
    "description": null,
    "builtinExternal": true
  },
  {
    "__docId__": 32,
    "kind": "external",
    "static": true,
    "variation": null,
    "name": "Boolean",
    "externalLink": "https://developer.mozilla.org/en-US/docs/Web/JavaScript/Reference/Global_Objects/Boolean",
    "memberof": "BuiltinExternal/ECMAScriptExternal.js",
    "longname": "BuiltinExternal/ECMAScriptExternal.js~Boolean",
    "access": null,
    "description": null,
    "builtinExternal": true
  },
  {
    "__docId__": 33,
    "kind": "external",
    "static": true,
    "variation": null,
    "name": "boolean",
    "externalLink": "https://developer.mozilla.org/en-US/docs/Web/JavaScript/Reference/Global_Objects/Boolean",
    "memberof": "BuiltinExternal/ECMAScriptExternal.js",
    "longname": "BuiltinExternal/ECMAScriptExternal.js~boolean",
    "access": null,
    "description": null,
    "builtinExternal": true
  },
  {
    "__docId__": 34,
    "kind": "external",
    "static": true,
    "variation": null,
    "name": "Symbol",
    "externalLink": "https://developer.mozilla.org/en-US/docs/Web/JavaScript/Reference/Global_Objects/Symbol",
    "memberof": "BuiltinExternal/ECMAScriptExternal.js",
    "longname": "BuiltinExternal/ECMAScriptExternal.js~Symbol",
    "access": null,
    "description": null,
    "builtinExternal": true
  },
  {
    "__docId__": 35,
    "kind": "external",
    "static": true,
    "variation": null,
    "name": "Error",
    "externalLink": "https://developer.mozilla.org/en-US/docs/Web/JavaScript/Reference/Global_Objects/Error",
    "memberof": "BuiltinExternal/ECMAScriptExternal.js",
    "longname": "BuiltinExternal/ECMAScriptExternal.js~Error",
    "access": null,
    "description": null,
    "builtinExternal": true
  },
  {
    "__docId__": 36,
    "kind": "external",
    "static": true,
    "variation": null,
    "name": "EvalError",
    "externalLink": "https://developer.mozilla.org/en-US/docs/Web/JavaScript/Reference/Global_Objects/EvalError",
    "memberof": "BuiltinExternal/ECMAScriptExternal.js",
    "longname": "BuiltinExternal/ECMAScriptExternal.js~EvalError",
    "access": null,
    "description": null,
    "builtinExternal": true
  },
  {
    "__docId__": 37,
    "kind": "external",
    "static": true,
    "variation": null,
    "name": "InternalError",
    "externalLink": "https://developer.mozilla.org/en-US/docs/Web/JavaScript/Reference/Global_Objects/InternalError",
    "memberof": "BuiltinExternal/ECMAScriptExternal.js",
    "longname": "BuiltinExternal/ECMAScriptExternal.js~InternalError",
    "access": null,
    "description": null,
    "builtinExternal": true
  },
  {
    "__docId__": 38,
    "kind": "external",
    "static": true,
    "variation": null,
    "name": "RangeError",
    "externalLink": "https://developer.mozilla.org/en-US/docs/Web/JavaScript/Reference/Global_Objects/RangeError",
    "memberof": "BuiltinExternal/ECMAScriptExternal.js",
    "longname": "BuiltinExternal/ECMAScriptExternal.js~RangeError",
    "access": null,
    "description": null,
    "builtinExternal": true
  },
  {
    "__docId__": 39,
    "kind": "external",
    "static": true,
    "variation": null,
    "name": "ReferenceError",
    "externalLink": "https://developer.mozilla.org/en-US/docs/Web/JavaScript/Reference/Global_Objects/ReferenceError",
    "memberof": "BuiltinExternal/ECMAScriptExternal.js",
    "longname": "BuiltinExternal/ECMAScriptExternal.js~ReferenceError",
    "access": null,
    "description": null,
    "builtinExternal": true
  },
  {
    "__docId__": 40,
    "kind": "external",
    "static": true,
    "variation": null,
    "name": "SyntaxError",
    "externalLink": "https://developer.mozilla.org/en-US/docs/Web/JavaScript/Reference/Global_Objects/SyntaxError",
    "memberof": "BuiltinExternal/ECMAScriptExternal.js",
    "longname": "BuiltinExternal/ECMAScriptExternal.js~SyntaxError",
    "access": null,
    "description": null,
    "builtinExternal": true
  },
  {
    "__docId__": 41,
    "kind": "external",
    "static": true,
    "variation": null,
    "name": "TypeError",
    "externalLink": "https://developer.mozilla.org/en-US/docs/Web/JavaScript/Reference/Global_Objects/TypeError",
    "memberof": "BuiltinExternal/ECMAScriptExternal.js",
    "longname": "BuiltinExternal/ECMAScriptExternal.js~TypeError",
    "access": null,
    "description": null,
    "builtinExternal": true
  },
  {
    "__docId__": 42,
    "kind": "external",
    "static": true,
    "variation": null,
    "name": "URIError",
    "externalLink": "https://developer.mozilla.org/en-US/docs/Web/JavaScript/Reference/Global_Objects/URIError",
    "memberof": "BuiltinExternal/ECMAScriptExternal.js",
    "longname": "BuiltinExternal/ECMAScriptExternal.js~URIError",
    "access": null,
    "description": null,
    "builtinExternal": true
  },
  {
    "__docId__": 43,
    "kind": "external",
    "static": true,
    "variation": null,
    "name": "Number",
    "externalLink": "https://developer.mozilla.org/en-US/docs/Web/JavaScript/Reference/Global_Objects/Number",
    "memberof": "BuiltinExternal/ECMAScriptExternal.js",
    "longname": "BuiltinExternal/ECMAScriptExternal.js~Number",
    "access": null,
    "description": null,
    "builtinExternal": true
  },
  {
    "__docId__": 44,
    "kind": "external",
    "static": true,
    "variation": null,
    "name": "number",
    "externalLink": "https://developer.mozilla.org/en-US/docs/Web/JavaScript/Reference/Global_Objects/Number",
    "memberof": "BuiltinExternal/ECMAScriptExternal.js",
    "longname": "BuiltinExternal/ECMAScriptExternal.js~number",
    "access": null,
    "description": null,
    "builtinExternal": true
  },
  {
    "__docId__": 45,
    "kind": "external",
    "static": true,
    "variation": null,
    "name": "Date",
    "externalLink": "https://developer.mozilla.org/en-US/docs/Web/JavaScript/Reference/Global_Objects/Date",
    "memberof": "BuiltinExternal/ECMAScriptExternal.js",
    "longname": "BuiltinExternal/ECMAScriptExternal.js~Date",
    "access": null,
    "description": null,
    "builtinExternal": true
  },
  {
    "__docId__": 46,
    "kind": "external",
    "static": true,
    "variation": null,
    "name": "String",
    "externalLink": "https://developer.mozilla.org/en-US/docs/Web/JavaScript/Reference/Global_Objects/String",
    "memberof": "BuiltinExternal/ECMAScriptExternal.js",
    "longname": "BuiltinExternal/ECMAScriptExternal.js~String",
    "access": null,
    "description": null,
    "builtinExternal": true
  },
  {
    "__docId__": 47,
    "kind": "external",
    "static": true,
    "variation": null,
    "name": "string",
    "externalLink": "https://developer.mozilla.org/en-US/docs/Web/JavaScript/Reference/Global_Objects/String",
    "memberof": "BuiltinExternal/ECMAScriptExternal.js",
    "longname": "BuiltinExternal/ECMAScriptExternal.js~string",
    "access": null,
    "description": null,
    "builtinExternal": true
  },
  {
    "__docId__": 48,
    "kind": "external",
    "static": true,
    "variation": null,
    "name": "RegExp",
    "externalLink": "https://developer.mozilla.org/en-US/docs/Web/JavaScript/Reference/Global_Objects/RegExp",
    "memberof": "BuiltinExternal/ECMAScriptExternal.js",
    "longname": "BuiltinExternal/ECMAScriptExternal.js~RegExp",
    "access": null,
    "description": null,
    "builtinExternal": true
  },
  {
    "__docId__": 49,
    "kind": "external",
    "static": true,
    "variation": null,
    "name": "Array",
    "externalLink": "https://developer.mozilla.org/en-US/docs/Web/JavaScript/Reference/Global_Objects/Array",
    "memberof": "BuiltinExternal/ECMAScriptExternal.js",
    "longname": "BuiltinExternal/ECMAScriptExternal.js~Array",
    "access": null,
    "description": null,
    "builtinExternal": true
  },
  {
    "__docId__": 50,
    "kind": "external",
    "static": true,
    "variation": null,
    "name": "Int8Array",
    "externalLink": "https://developer.mozilla.org/en-US/docs/Web/JavaScript/Reference/Global_Objects/Int8Array",
    "memberof": "BuiltinExternal/ECMAScriptExternal.js",
    "longname": "BuiltinExternal/ECMAScriptExternal.js~Int8Array",
    "access": null,
    "description": null,
    "builtinExternal": true
  },
  {
    "__docId__": 51,
    "kind": "external",
    "static": true,
    "variation": null,
    "name": "Uint8Array",
    "externalLink": "https://developer.mozilla.org/en-US/docs/Web/JavaScript/Reference/Global_Objects/Uint8Array",
    "memberof": "BuiltinExternal/ECMAScriptExternal.js",
    "longname": "BuiltinExternal/ECMAScriptExternal.js~Uint8Array",
    "access": null,
    "description": null,
    "builtinExternal": true
  },
  {
    "__docId__": 52,
    "kind": "external",
    "static": true,
    "variation": null,
    "name": "Uint8ClampedArray",
    "externalLink": "https://developer.mozilla.org/en-US/docs/Web/JavaScript/Reference/Global_Objects/Uint8ClampedArray",
    "memberof": "BuiltinExternal/ECMAScriptExternal.js",
    "longname": "BuiltinExternal/ECMAScriptExternal.js~Uint8ClampedArray",
    "access": null,
    "description": null,
    "builtinExternal": true
  },
  {
    "__docId__": 53,
    "kind": "external",
    "static": true,
    "variation": null,
    "name": "Int16Array",
    "externalLink": "https://developer.mozilla.org/en-US/docs/Web/JavaScript/Reference/Global_Objects/Int16Array",
    "memberof": "BuiltinExternal/ECMAScriptExternal.js",
    "longname": "BuiltinExternal/ECMAScriptExternal.js~Int16Array",
    "access": null,
    "description": null,
    "builtinExternal": true
  },
  {
    "__docId__": 54,
    "kind": "external",
    "static": true,
    "variation": null,
    "name": "Uint16Array",
    "externalLink": "https://developer.mozilla.org/en-US/docs/Web/JavaScript/Reference/Global_Objects/Uint16Array",
    "memberof": "BuiltinExternal/ECMAScriptExternal.js",
    "longname": "BuiltinExternal/ECMAScriptExternal.js~Uint16Array",
    "access": null,
    "description": null,
    "builtinExternal": true
  },
  {
    "__docId__": 55,
    "kind": "external",
    "static": true,
    "variation": null,
    "name": "Int32Array",
    "externalLink": "https://developer.mozilla.org/en-US/docs/Web/JavaScript/Reference/Global_Objects/Int32Array",
    "memberof": "BuiltinExternal/ECMAScriptExternal.js",
    "longname": "BuiltinExternal/ECMAScriptExternal.js~Int32Array",
    "access": null,
    "description": null,
    "builtinExternal": true
  },
  {
    "__docId__": 56,
    "kind": "external",
    "static": true,
    "variation": null,
    "name": "Uint32Array",
    "externalLink": "https://developer.mozilla.org/en-US/docs/Web/JavaScript/Reference/Global_Objects/Uint32Array",
    "memberof": "BuiltinExternal/ECMAScriptExternal.js",
    "longname": "BuiltinExternal/ECMAScriptExternal.js~Uint32Array",
    "access": null,
    "description": null,
    "builtinExternal": true
  },
  {
    "__docId__": 57,
    "kind": "external",
    "static": true,
    "variation": null,
    "name": "Float32Array",
    "externalLink": "https://developer.mozilla.org/en-US/docs/Web/JavaScript/Reference/Global_Objects/Float32Array",
    "memberof": "BuiltinExternal/ECMAScriptExternal.js",
    "longname": "BuiltinExternal/ECMAScriptExternal.js~Float32Array",
    "access": null,
    "description": null,
    "builtinExternal": true
  },
  {
    "__docId__": 58,
    "kind": "external",
    "static": true,
    "variation": null,
    "name": "Float64Array",
    "externalLink": "https://developer.mozilla.org/en-US/docs/Web/JavaScript/Reference/Global_Objects/Float64Array",
    "memberof": "BuiltinExternal/ECMAScriptExternal.js",
    "longname": "BuiltinExternal/ECMAScriptExternal.js~Float64Array",
    "access": null,
    "description": null,
    "builtinExternal": true
  },
  {
    "__docId__": 59,
    "kind": "external",
    "static": true,
    "variation": null,
    "name": "Map",
    "externalLink": "https://developer.mozilla.org/en-US/docs/Web/JavaScript/Reference/Global_Objects/Map",
    "memberof": "BuiltinExternal/ECMAScriptExternal.js",
    "longname": "BuiltinExternal/ECMAScriptExternal.js~Map",
    "access": null,
    "description": null,
    "builtinExternal": true
  },
  {
    "__docId__": 60,
    "kind": "external",
    "static": true,
    "variation": null,
    "name": "Set",
    "externalLink": "https://developer.mozilla.org/en-US/docs/Web/JavaScript/Reference/Global_Objects/Set",
    "memberof": "BuiltinExternal/ECMAScriptExternal.js",
    "longname": "BuiltinExternal/ECMAScriptExternal.js~Set",
    "access": null,
    "description": null,
    "builtinExternal": true
  },
  {
    "__docId__": 61,
    "kind": "external",
    "static": true,
    "variation": null,
    "name": "WeakMap",
    "externalLink": "https://developer.mozilla.org/en-US/docs/Web/JavaScript/Reference/Global_Objects/WeakMap",
    "memberof": "BuiltinExternal/ECMAScriptExternal.js",
    "longname": "BuiltinExternal/ECMAScriptExternal.js~WeakMap",
    "access": null,
    "description": null,
    "builtinExternal": true
  },
  {
    "__docId__": 62,
    "kind": "external",
    "static": true,
    "variation": null,
    "name": "WeakSet",
    "externalLink": "https://developer.mozilla.org/en-US/docs/Web/JavaScript/Reference/Global_Objects/WeakSet",
    "memberof": "BuiltinExternal/ECMAScriptExternal.js",
    "longname": "BuiltinExternal/ECMAScriptExternal.js~WeakSet",
    "access": null,
    "description": null,
    "builtinExternal": true
  },
  {
    "__docId__": 63,
    "kind": "external",
    "static": true,
    "variation": null,
    "name": "ArrayBuffer",
    "externalLink": "https://developer.mozilla.org/en-US/docs/Web/JavaScript/Reference/Global_Objects/ArrayBuffer",
    "memberof": "BuiltinExternal/ECMAScriptExternal.js",
    "longname": "BuiltinExternal/ECMAScriptExternal.js~ArrayBuffer",
    "access": null,
    "description": null,
    "builtinExternal": true
  },
  {
    "__docId__": 64,
    "kind": "external",
    "static": true,
    "variation": null,
    "name": "DataView",
    "externalLink": "https://developer.mozilla.org/en-US/docs/Web/JavaScript/Reference/Global_Objects/DataView",
    "memberof": "BuiltinExternal/ECMAScriptExternal.js",
    "longname": "BuiltinExternal/ECMAScriptExternal.js~DataView",
    "access": null,
    "description": null,
    "builtinExternal": true
  },
  {
    "__docId__": 65,
    "kind": "external",
    "static": true,
    "variation": null,
    "name": "JSON",
    "externalLink": "https://developer.mozilla.org/en-US/docs/Web/JavaScript/Reference/Global_Objects/JSON",
    "memberof": "BuiltinExternal/ECMAScriptExternal.js",
    "longname": "BuiltinExternal/ECMAScriptExternal.js~JSON",
    "access": null,
    "description": null,
    "builtinExternal": true
  },
  {
    "__docId__": 66,
    "kind": "external",
    "static": true,
    "variation": null,
    "name": "Promise",
    "externalLink": "https://developer.mozilla.org/en-US/docs/Web/JavaScript/Reference/Global_Objects/Promise",
    "memberof": "BuiltinExternal/ECMAScriptExternal.js",
    "longname": "BuiltinExternal/ECMAScriptExternal.js~Promise",
    "access": null,
    "description": null,
    "builtinExternal": true
  },
  {
    "__docId__": 67,
    "kind": "external",
    "static": true,
    "variation": null,
    "name": "Generator",
    "externalLink": "https://developer.mozilla.org/en-US/docs/Web/JavaScript/Reference/Global_Objects/Generator",
    "memberof": "BuiltinExternal/ECMAScriptExternal.js",
    "longname": "BuiltinExternal/ECMAScriptExternal.js~Generator",
    "access": null,
    "description": null,
    "builtinExternal": true
  },
  {
    "__docId__": 68,
    "kind": "external",
    "static": true,
    "variation": null,
    "name": "GeneratorFunction",
    "externalLink": "https://developer.mozilla.org/en-US/docs/Web/JavaScript/Reference/Global_Objects/GeneratorFunction",
    "memberof": "BuiltinExternal/ECMAScriptExternal.js",
    "longname": "BuiltinExternal/ECMAScriptExternal.js~GeneratorFunction",
    "access": null,
    "description": null,
    "builtinExternal": true
  },
  {
    "__docId__": 69,
    "kind": "external",
    "static": true,
    "variation": null,
    "name": "Reflect",
    "externalLink": "https://developer.mozilla.org/en-US/docs/Web/JavaScript/Reference/Global_Objects/Reflect",
    "memberof": "BuiltinExternal/ECMAScriptExternal.js",
    "longname": "BuiltinExternal/ECMAScriptExternal.js~Reflect",
    "access": null,
    "description": null,
    "builtinExternal": true
  },
  {
    "__docId__": 70,
    "kind": "external",
    "static": true,
    "variation": null,
    "name": "Proxy",
    "externalLink": "https://developer.mozilla.org/en-US/docs/Web/JavaScript/Reference/Global_Objects/Proxy",
    "memberof": "BuiltinExternal/ECMAScriptExternal.js",
    "longname": "BuiltinExternal/ECMAScriptExternal.js~Proxy",
    "access": null,
    "description": null,
    "builtinExternal": true
  },
  {
    "__docId__": 72,
    "kind": "external",
    "static": true,
    "variation": null,
    "name": "CanvasRenderingContext2D",
    "externalLink": "https://developer.mozilla.org/en-US/docs/Web/API/CanvasRenderingContext2D",
    "memberof": "BuiltinExternal/WebAPIExternal.js",
    "longname": "BuiltinExternal/WebAPIExternal.js~CanvasRenderingContext2D",
    "access": null,
    "description": null,
    "builtinExternal": true
  },
  {
    "__docId__": 73,
    "kind": "external",
    "static": true,
    "variation": null,
    "name": "DocumentFragment",
    "externalLink": "https://developer.mozilla.org/en-US/docs/Web/API/DocumentFragment",
    "memberof": "BuiltinExternal/WebAPIExternal.js",
    "longname": "BuiltinExternal/WebAPIExternal.js~DocumentFragment",
    "access": null,
    "description": null,
    "builtinExternal": true
  },
  {
    "__docId__": 74,
    "kind": "external",
    "static": true,
    "variation": null,
    "name": "Element",
    "externalLink": "https://developer.mozilla.org/en-US/docs/Web/API/Element",
    "memberof": "BuiltinExternal/WebAPIExternal.js",
    "longname": "BuiltinExternal/WebAPIExternal.js~Element",
    "access": null,
    "description": null,
    "builtinExternal": true
  },
  {
    "__docId__": 75,
    "kind": "external",
    "static": true,
    "variation": null,
    "name": "Event",
    "externalLink": "https://developer.mozilla.org/en-US/docs/Web/API/Event",
    "memberof": "BuiltinExternal/WebAPIExternal.js",
    "longname": "BuiltinExternal/WebAPIExternal.js~Event",
    "access": null,
    "description": null,
    "builtinExternal": true
  },
  {
    "__docId__": 76,
    "kind": "external",
    "static": true,
    "variation": null,
    "name": "Node",
    "externalLink": "https://developer.mozilla.org/en-US/docs/Web/API/Node",
    "memberof": "BuiltinExternal/WebAPIExternal.js",
    "longname": "BuiltinExternal/WebAPIExternal.js~Node",
    "access": null,
    "description": null,
    "builtinExternal": true
  },
  {
    "__docId__": 77,
    "kind": "external",
    "static": true,
    "variation": null,
    "name": "NodeList",
    "externalLink": "https://developer.mozilla.org/en-US/docs/Web/API/NodeList",
    "memberof": "BuiltinExternal/WebAPIExternal.js",
    "longname": "BuiltinExternal/WebAPIExternal.js~NodeList",
    "access": null,
    "description": null,
    "builtinExternal": true
  },
  {
    "__docId__": 78,
    "kind": "external",
    "static": true,
    "variation": null,
    "name": "XMLHttpRequest",
    "externalLink": "https://developer.mozilla.org/en/docs/Web/API/XMLHttpRequest",
    "memberof": "BuiltinExternal/WebAPIExternal.js",
    "longname": "BuiltinExternal/WebAPIExternal.js~XMLHttpRequest",
    "access": null,
    "description": null,
    "builtinExternal": true
  },
  {
    "__docId__": 79,
    "kind": "external",
    "static": true,
    "variation": null,
    "name": "AudioContext",
    "externalLink": "https://developer.mozilla.org/en/docs/Web/API/AudioContext",
    "memberof": "BuiltinExternal/WebAPIExternal.js",
    "longname": "BuiltinExternal/WebAPIExternal.js~AudioContext",
    "access": null,
    "description": null,
    "builtinExternal": true
  }
]